X100GeGdbXiaoJiqiao/README.md
X100GeGdbXiaoJiqiao/__init__.py
X100GeGdbXiaoJiqiao/__main__.py
X100GeGdbXiaoJiqiao/file.epub
X100GeGdbXiaoJiqiao/index.html
X100GeGdbXiaoJiqiao/css/__init__.py
X100GeGdbXiaoJiqiao/css/annotations.css
X100GeGdbXiaoJiqiao/css/main.css
X100GeGdbXiaoJiqiao/css/normalize.css
X100GeGdbXiaoJiqiao/css/popup.css
X100GeGdbXiaoJiqiao/font/__init__.py
X100GeGdbXiaoJiqiao/font/fontello.eot
X100GeGdbXiaoJiqiao/font/fontello.svg
X100GeGdbXiaoJiqiao/font/fontello.ttf
X100GeGdbXiaoJiqiao/font/fontello.woff
X100GeGdbXiaoJiqiao/img/__init__.py
X100GeGdbXiaoJiqiao/img/annotator-glyph-sprite.png
X100GeGdbXiaoJiqiao/img/annotator-icon-sprite.png
X100GeGdbXiaoJiqiao/img/apple-touch-icon.png
X100GeGdbXiaoJiqiao/img/cancelfullscreen.png
X100GeGdbXiaoJiqiao/img/close.png
X100GeGdbXiaoJiqiao/img/fullscreen.png
X100GeGdbXiaoJiqiao/img/loader.gif
X100GeGdbXiaoJiqiao/img/menu-icon.png
X100GeGdbXiaoJiqiao/img/save.png
X100GeGdbXiaoJiqiao/img/saved.png
X100GeGdbXiaoJiqiao/img/settings-s.png
X100GeGdbXiaoJiqiao/img/settings.png
X100GeGdbXiaoJiqiao/img/star.png
X100GeGdbXiaoJiqiao/js/__init__.py
X100GeGdbXiaoJiqiao/js/epub.js
X100GeGdbXiaoJiqiao/js/epub.min.js
X100GeGdbXiaoJiqiao/js/epub.min.map
X100GeGdbXiaoJiqiao/js/hooks.min.js
X100GeGdbXiaoJiqiao/js/hooks.min.map
X100GeGdbXiaoJiqiao/js/reader.js
X100GeGdbXiaoJiqiao/js/reader.js.map
X100GeGdbXiaoJiqiao/js/reader.min.js
X100GeGdbXiaoJiqiao/js/reader.min.map
X100GeGdbXiaoJiqiao/js/hooks/__init__.py
X100GeGdbXiaoJiqiao/js/hooks/extensions/__init__.py
X100GeGdbXiaoJiqiao/js/hooks/extensions/highlight.js
X100GeGdbXiaoJiqiao/js/libs/__init__.py
X100GeGdbXiaoJiqiao/js/libs/jquery.min.js
X100GeGdbXiaoJiqiao/js/libs/localforage.min.js
X100GeGdbXiaoJiqiao/js/libs/screenfull.js
X100GeGdbXiaoJiqiao/js/libs/screenfull.min.js
X100GeGdbXiaoJiqiao/js/libs/zip.min.js
X100GeGdbXiaoJiqiao/js/plugins/__init__.py
X100GeGdbXiaoJiqiao/js/plugins/hypothesis.js
X100GeGdbXiaoJiqiao/js/plugins/search.js
x100_ge_gdb_xiao_jiqiao-2024.2.29.0.dist-info/METADATA
x100_ge_gdb_xiao_jiqiao-2024.2.29.0.dist-info/WHEEL
x100_ge_gdb_xiao_jiqiao-2024.2.29.0.dist-info/entry_points.txt
x100_ge_gdb_xiao_jiqiao-2024.2.29.0.dist-info/top_level.txt
x100_ge_gdb_xiao_jiqiao-2024.2.29.0.dist-info/RECORD
